codel
