Metadata-Version: 2.1
Name: codel
Version: 1.1.1
Summary: Count lines of your code tastefully.
Home-page: https://github.com/VoIlAlex/codel
Author: voilalex
Author-email: ilya.vouk@gmail.com
License: MIT
Download-URL: https://github.com/VoIlAlex/codel/archive/v1.1.1.tag.gz
Keywords: cli,code,lines,performance,utility
Platform: UNKNOWN
Classifier: Environment :: Console
Classifier: Intended Audience :: Developers
Classifier: Topic :: Utilities
Classifier: Programming Language :: Python :: 3.4
Classifier: Programming Language :: Python :: 3.5
Classifier: Programming Language :: Python :: 3.6
Classifier: Programming Language :: Python :: 3.7
Classifier: Programming Language :: Python :: 3.8
